aiohttp_jinja2_haggle.py
aiohttp_jinja2_haggle-0.0.0.dist-info/METADATA
aiohttp_jinja2_haggle-0.0.0.dist-info/WHEEL
aiohttp_jinja2_haggle-0.0.0.dist-info/top_level.txt
aiohttp_jinja2_haggle-0.0.0.dist-info/RECORD
